groupthink/__init__.py
groupthink/commands.py
groupthink/version.py
groupthink/scripts/groupthink-script
groupthink-1.0.0.dist-info/DESCRIPTION.rst
groupthink-1.0.0.dist-info/entry_points.txt
groupthink-1.0.0.dist-info/METADATA
groupthink-1.0.0.dist-info/metadata.json
groupthink-1.0.0.dist-info/RECORD
groupthink-1.0.0.dist-info/top_level.txt
groupthink-1.0.0.dist-info/WHEEL
tests/__init__.py
tests/groupthink_tests.py
