Metadata-Version: 2.0
Name: groupthink
Version: 1.0.0
Summary: Install, update, and manage GitHub organization-specific command line scripts
Home-page: https://github.com/emanuelfeld/groupthink
Author: Emanuel Feld
Author-email: elefbet@gmail.com
License: CC0-1.0
Keywords: git cli console github
Platform: UNKNOWN
Classifier: Development Status :: 4 - Beta
Classifier: Intended Audience :: Developers
Classifier: License :: CC0 1.0 Universal (CC0 1.0) Public Domain Dedication
Classifier: Natural Language :: English
Classifier: Programming Language :: Python :: 2.7
Classifier: Programming Language :: Python :: 3.3
Classifier: Programming Language :: Python :: 3.4
Classifier: Operating System :: OS Independent
Requires-Dist: argh
Requires-Dist: requests
